capone/__init__.py
capone/exceptions.py
capone/models.py
capone/utils.py
capone/api/__init__.py
capone/api/actions.py
capone/api/queries.py
capone/migrations/0001_initial.py
capone/migrations/__init__.py
capone/tests/__init__.py
capone/tests/factories.py
capone/tests/models.py
capone/tests/settings.py
capone/tests/test_assert_transaction_in_ledgers_for_amounts_with_evidence.py
capone/tests/test_create_transaction.py
capone/tests/test_factories.py
capone/tests/test_filter_by_related_objects.py
capone/tests/test_ledger_balances.py
capone/tests/test_transaction_model.py
capone/tests/test_void.py
capone/tests/migrations/0001_initial.py
capone/tests/migrations/__init__.py
capone-3.1.0.dist-info/AUTHORS
capone-3.1.0.dist-info/LICENSE
capone-3.1.0.dist-info/METADATA
capone-3.1.0.dist-info/WHEEL
capone-3.1.0.dist-info/pbr.json
capone-3.1.0.dist-info/top_level.txt
capone-3.1.0.dist-info/RECORD
